encryption.py
plxscripting/__init__.py
plxscripting/__version__.py
plxscripting/connection.py
plxscripting/console.py
plxscripting/const.py
plxscripting/easy.py
plxscripting/error_mode.py
plxscripting/image.py
plxscripting/interactive.py
plxscripting/logger.py
plxscripting/plaxis_connector.py
plxscripting/plaxis_jupyter_kernel.py
plxscripting/plx_scripting_exceptions.py
plxscripting/plxobjects.py
plxscripting/plxproxy.py
plxscripting/plxproxyfactory.py
plxscripting/run_jupyter.py
plxscripting/selection.py
plxscripting/server.py
plxscripting/tokenizer.py
plxscripting/utils.py
plxscripting/win32_plxutils.py
plxscripting/unittests/__init__.py
plxscripting/unittests/mock_connection.py
plxscripting/unittests/mock_server.py
plxscripting/unittests/test_plxproxy.py
plxscripting/unittests/test_selection.py
plxscripting/unittests/test_server.py
plxscripting/unittests/test_tokenizer.py
plxscripting-1.0.4.dist-info/LICENSE
plxscripting-1.0.4.dist-info/METADATA
plxscripting-1.0.4.dist-info/WHEEL
plxscripting-1.0.4.dist-info/top_level.txt
plxscripting-1.0.4.dist-info/RECORD
