Metadata-Version: 2.1
Name: plxscripting
Version: 1.0.4
Summary: Python files required to interact with PLAXIS API
License: Plaxis Public License 1.0 (PPL-1.0)
Project-URL: repository, https://github.com/cemsbv/plxscripting
Keywords: plxscripting,PLAXIS,CEMS
Requires-Python: >=3.9
License-File: LICENSE
Requires-Dist: requests <3.0,>=2.28
Requires-Dist: pycryptodome <4.0,>=3.11.0
Requires-Dist: psutil <6.0,>=5.7.2
Requires-Dist: ipykernel >=6.21.2
Provides-Extra: test
Requires-Dist: coveralls ; extra == 'test'
Requires-Dist: pytest ; extra == 'test'
